MANIFEST.in
README.md
setup.py
mdc_nava/__init__.py
mdc_nava/_imports_.py
mdc_nava/example_component.py
mdc_nava/mdc_nava.dev.js
mdc_nava/mdc_nava.min.js
mdc_nava/metadata.json
mdc_nava/package.json
mdc_nava.egg-info/PKG-INFO
mdc_nava.egg-info/SOURCES.txt
mdc_nava.egg-info/dependency_links.txt
mdc_nava.egg-info/top_level.txt