Metadata-Version: 1.0
Name: mdc-nava
Version: 0.0.1
Summary: i try building a dash component
Home-page: UNKNOWN
Author: Abhinava Shriraam abhinava1206@gmail.com
Author-email: UNKNOWN
License: MIT
Platform: UNKNOWN
